pdb2xyz/__init__.py
pdb2xyz/py.typed
pdb2xyz-0.3.0.dist-info/METADATA
pdb2xyz-0.3.0.dist-info/WHEEL
pdb2xyz-0.3.0.dist-info/entry_points.txt
pdb2xyz-0.3.0.dist-info/licenses/LICENSE
pdb2xyz-0.3.0.dist-info/RECORD
