Metadata-Version: 2.4
Name: pdb2xyz
Version: 0.3.0
Summary: Convert PDB structures to coarse grained XYZ files
Author: Mikael Lund
License: Apache-2.0
License-File: LICENSE
Requires-Python: >=3.10
Requires-Dist: jinja2>=3.1.6
Requires-Dist: mdtraj>=1.10.3
